cadelphi/__init__.py
cadelphi/__main__.py
cadelphi/app.py
cadelphi/database.py
cadelphi/i18n.py
cadelphi/models.py
cadelphi/sample_data.py
cadelphi/security.py
cadelphi/utils.py
cadelphi/sample_data/__init__.py
cadelphi/sample_data/english.py
cadelphi/sample_data/turkish.py
cadelphi/static/css/normalize.css
cadelphi/static/css/style.css
cadelphi/static/js/admin_graph.js
cadelphi/templates/admin_dashboard.html
cadelphi/templates/admin_graph.html
cadelphi/templates/admin_login.html
cadelphi/templates/admin_settings.html
cadelphi/templates/base.html
cadelphi/templates/index.html
cadelphi/templates/participate_complete.html
cadelphi/templates/participate_session.html
cadelphi/templates/participate_start.html
cadelphi-0.2.2.dist-info/licenses/LICENSE
cadelphi-0.2.2.dist-info/METADATA
cadelphi-0.2.2.dist-info/WHEEL
cadelphi-0.2.2.dist-info/entry_points.txt
cadelphi-0.2.2.dist-info/top_level.txt
cadelphi-0.2.2.dist-info/RECORD
