Metadata-Version: 2.4
Name: cadelphi
Version: 0.2.2
Summary: Computerized Argument Delphi experimentation toolkit
Author-email: Sadi Evren SEKER <cadelphi@sadievrenseker.com>
License-Expression: MIT
Project-URL: Homepage, https://github.com/sadievrenseker/cadelphi
Requires-Python: >=3.9
License-File: LICENSE
Requires-Dist: fastapi>=0.110
Requires-Dist: uvicorn[standard]>=0.27
Requires-Dist: sqlalchemy>=2.0
Requires-Dist: jinja2>=3.1
Requires-Dist: python-multipart>=0.0.6
Requires-Dist: itsdangerous>=2.1
Requires-Dist: passlib[argon2]>=1.7
Requires-Dist: argon2-cffi>=21.3
Dynamic: license-file
